__init__.py
main.py
wappscan/__init__.py
wappscan/api.py
wappscan/cli.py
wappscan/exceptions.py
wappscan-0.0.10.dist-info/LICENSE
wappscan-0.0.10.dist-info/METADATA
wappscan-0.0.10.dist-info/WHEEL
wappscan-0.0.10.dist-info/entry_points.txt
wappscan-0.0.10.dist-info/top_level.txt
wappscan-0.0.10.dist-info/RECORD
