Metadata-Version: 2.2
Name: wappscan
Version: 0.0.10
Summary: Scan web apps from your code.
Author-email: "Pentest-Tools.com" <contact@pentest-tools.com>
License:                     GNU GENERAL PUBLIC LICENSE
Requires-Python: >=3.9
License-File: LICENSE
Requires-Dist: requests
Requires-Dist: rich
Requires-Dist: typer
